table_column_doris/__init__.py
table_column_doris-0.3.0.dist-info/WHEEL
table_column_doris-0.3.0.dist-info/METADATA
table_column_doris-0.3.0.dist-info/RECORD
